byquant/__init__.py
byquant/bybacktest.py
byquant/bystrategy.py
byquant/help.py
byquant/setting.py
byquant/analysis/__init__.py
byquant/analysis/byanalysis.py
byquant/auth/__init__.py
byquant/auth/byauth.py
byquant/bybot/__init__.py
byquant/bybot/algo/__init__.py
byquant/bybot/algo/bias.py
byquant/bybot/algo/cmi.py
byquant/bybot/algo/dladder.py
byquant/bybot/algo/donchian.py
byquant/bybot/algo/dualthrust.py
byquant/bybot/algo/emv.py
byquant/bybot/algo/keltner.py
byquant/bybot/algo/phalifo.py
byquant/bybot/algo/rbreaker.py
byquant/bybot/lib/__init__.py
byquant/bybot/lib/backtest.py
byquant/bybot/lib/bymetrics.py
byquant/bybot/lib/sharpe_drawdown_return.py
byquant/bybot/model/__init__.py
byquant/bybot/model/ada_boost_regressor.py
byquant/bybot/model/bagging_regressor.py
byquant/bybot/model/base.py
byquant/bybot/model/decision_tree_regressor.py
byquant/bybot/model/extra_trees_regressor.py
byquant/bybot/model/gradient_boosting_regressor.py
byquant/bybot/model/k_neighbors_regressor.py
byquant/bybot/model/lars.py
byquant/bybot/model/linear_regression.py
byquant/bybot/model/linear_svr.py
byquant/bybot/model/mlp_regressor.py
byquant/bybot/model/random_forest_regressor.py
byquant/bybot/signal/__init__.py
byquant/bybot/signal/adx.py
byquant/bybot/signal/atr.py
byquant/bybot/signal/bbands.py
byquant/bybot/signal/bias.py
byquant/bybot/signal/cci.py
byquant/bybot/signal/cmi.py
byquant/bybot/signal/dladder.py
byquant/bybot/signal/donchian.py
byquant/bybot/signal/dualthrust.py
byquant/bybot/signal/kama.py
byquant/bybot/signal/keltner.py
byquant/bybot/signal/macd.py
byquant/bybot/signal/phalifo.py
byquant/bybot/signal/rbreaker.py
byquant/bybot/signal/rsi.py
byquant/bybot/store/__init__.py
byquant/bybot/store/ccxt/__init__.py
byquant/bybot/store/ccxt/broker.py
byquant/bybot/store/ccxt/feed.py
byquant/bybot/store/ccxt/store.py
byquant/bybot/store/ccxtcn/__init__.py
byquant/bybot/store/ccxtcn/broker.py
byquant/bybot/store/ccxtcn/feed.py
byquant/bybot/store/ccxtcn/store.py
byquant-3.12.116.0.dist-info/METADATA
byquant-3.12.116.0.dist-info/WHEEL
byquant-3.12.116.0.dist-info/top_level.txt
byquant-3.12.116.0.dist-info/RECORD
