Metadata-Version: 2.4
Name: byquant
Version: 3.12.116.0
Summary: byquant库由ByQuant.com 提供支持，可以回测及策略交易。ByQuant.com官网提供系列策略课程《量化策略百战案例》；ByQuant智能决策分析系统提供通过客户端方式调用该库功能！
Author-email: ByQuant <info@byquant.com>
License: GPL
Project-URL: Homepage, https://byquant.com
Keywords: quant,strategy,algorithmic,algotrading
Classifier: Development Status :: 4 - Beta
Classifier: Intended Audience :: Developers
Classifier: Intended Audience :: Financial and Insurance Industry
Classifier: Intended Audience :: Information Technology
Classifier: Topic :: Software Development :: Build Tools
Classifier: Topic :: Office/Business :: Financial :: Investment
Classifier: License :: OSI Approved :: MIT License
Classifier: Programming Language :: Python :: 3.8
Classifier: Programming Language :: Python :: 3.9
Classifier: Programming Language :: Python :: 3.10
Classifier: Programming Language :: Python :: 3.11
Classifier: Programming Language :: Python :: 3.12
Classifier: Operating System :: OS Independent
Classifier: Environment :: Console
Requires-Dist: requests
Requires-Dist: pandas
Requires-Dist: quantstats
Requires-Dist: IPython
Requires-Dist: tushare
Requires-Dist: akshare
Requires-Dist: baostock
Requires-Dist: backtrader
